["[{\"title\":\"\\u9577\\u91ce\\u767a \\u30c1\\u30d9\\u30c3\\u30c8\\u65c5\\u884c \\u30c1\\u30d9\\u30c3\\u30c8\\u30c4\\u30a2\\u30fc\\uff5c\\u6d77\\u5916\\u65c5\\u884c \\u6d77\\u5916\\u30c4\\u30a2\\u30fc\\uff5c\\u962a\\u6025\\u4ea4\\u901a\\u793e\",\"pageviews_x\":1,\"pagePath\":\"\\/china\\/tibet\\/\",\"region\":\"\\u9577\\u91ce\\u767a\",\"pageviews_y\":1},{\"title\":\"\\u9577\\u91ce\\u767a \\u97d3\\u56fd\\u65c5\\u884c \\u97d3\\u56fd\\u30c4\\u30a2\\u30fc\\uff5c\\u6d77\\u5916\\u65c5\\u884c \\u6d77\\u5916\\u30c4\\u30a2\\u30fc\\uff5c\\u962a\\u6025\\u4ea4\\u901a\\u793e\",\"pageviews_x\":2,\"pagePath\":\"\\/korea\\/\",\"region\":\"\\u9577\\u91ce\\u767a\",\"pageviews_y\":3},{\"title\":\"\\u9577\\u91ce\\u767a \\u30bd\\u30a6\\u30eb\\u65c5\\u884c \\u30bd\\u30a6\\u30eb\\u30c4\\u30a2\\u30fc\\uff5c\\u6d77\\u5916\\u65c5\\u884c \\u6d77\\u5916\\u30c4\\u30a2\\u30fc\\uff5c\\u962a\\u6025\\u4ea4\\u901a\\u793e\",\"pageviews_x\":1,\"pagePath\":\"\\/korea\\/seoul\\/\",\"region\":\"\\u9577\\u91ce\\u767a\",\"pageviews_y\":2},{\"title\":\"\\u9577\\u91ce\\u767a \\u6e08\\u5dde\\u5cf6\\u65c5\\u884c \\u6e08\\u5dde\\u5cf6\\u30c4\\u30a2\\u30fc\\uff5c\\u6d77\\u5916\\u65c5\\u884c \\u6d77\\u5916\\u30c4\\u30a2\\u30fc\\uff5c\\u962a\\u6025\\u4ea4\\u901a\\u793e\",\"pageviews_x\":1,\"pagePath\":\"\\/korea\\/jeju\\/\",\"region\":\"\\u9577\\u91ce\\u767a\",\"pageviews_y\":1},{\"title\":\"\\u9577\\u91ce\\u767a \\u53f0\\u6e7e\\u65c5\\u884c \\u53f0\\u6e7e\\u30c4\\u30a2\\u30fc\\uff5c\\u6d77\\u5916\\u65c5\\u884c \\u6d77\\u5916\\u30c4\\u30a2\\u30fc\\uff5c\\u962a\\u6025\\u4ea4\\u901a\\u793e\",\"pageviews_x\":5,\"pagePath\":\"\\/taiwan\\/\",\"region\":\"\\u9577\\u91ce\\u767a\",\"pageviews_y\":9},{\"title\":\"\\u9577\\u91ce\\u767a \\u53f0\\u5317\\u65c5\\u884c \\u53f0\\u5317\\u30c4\\u30a2\\u30fc\\uff5c\\u6d77\\u5916\\u65c5\\u884c \\u6d77\\u5916\\u30c4\\u30a2\\u30fc\\uff5c\\u962a\\u6025\\u4ea4\\u901a\\u793e\",\"pageviews_x\":3,\"pagePath\":\"\\/taiwan\\/taipei\\/\",\"region\":\"\\u9577\\u91ce\\u767a\",\"pageviews_y\":3},{\"title\":\"\\u9577\\u91ce\\u767a \\u30bf\\u30a4\\u65c5\\u884c \\u30bf\\u30a4\\u30c4\\u30a2\\u30fc\\uff5c\\u6d77\\u5916\\u65c5\\u884c \\u6d77\\u5916\\u30c4\\u30a2\\u30fc\\uff5c\\u962a\\u6025\\u4ea4\\u901a\\u793e\",\"pageviews_x\":2,\"pagePath\":\"\\/thailand\\/\",\"region\":\"\\u9577\\u91ce\\u767a\",\"pageviews_y\":2},{\"title\":\"\\u9577\\u91ce\\u767a \\u30b7\\u30f3\\u30ac\\u30dd\\u30fc\\u30eb\\u65c5\\u884c \\u30b7\\u30f3\\u30ac\\u30dd\\u30fc\\u30eb\\u30c4\\u30a2\\u30fc\\uff5c\\u6d77\\u5916\\u65c5\\u884c \\u6d77\\u5916\\u30c4\\u30a2\\u30fc\\uff5c\\u962a\\u6025\\u4ea4\\u901a\\u793e\",\"pageviews_x\":1,\"pagePath\":\"\\/singapore\\/\",\"region\":\"\\u9577\\u91ce\\u767a\",\"pageviews_y\":2},{\"title\":\"\\u9577\\u91ce\\u767a \\u30de\\u30ec\\u30fc\\u30b7\\u30a2\\u65c5\\u884c \\u30de\\u30ec\\u30fc\\u30b7\\u30a2\\u30c4\\u30a2\\u30fc\\uff5c\\u6d77\\u5916\\u65c5\\u884c \\u6d77\\u5916\\u30c4\\u30a2\\u30fc\\uff5c\\u962a\\u6025\\u4ea4\\u901a\\u793e\",\"pageviews_x\":1,\"pagePath\":\"\\/malaysia\\/\",\"region\":\"\\u9577\\u91ce\\u767a\",\"pageviews_y\":1},{\"title\":\"\\u9577\\u91ce\\u767a \\u30d9\\u30c8\\u30ca\\u30e0\\u65c5\\u884c \\u30d9\\u30c8\\u30ca\\u30e0\\u30c4\\u30a2\\u30fc\\uff5c\\u6d77\\u5916\\u65c5\\u884c \\u6d77\\u5916\\u30c4\\u30a2\\u30fc\\uff5c\\u962a\\u6025\\u4ea4\\u901a\\u793e\",\"pageviews_x\":1,\"pagePath\":\"\\/vietnam\\/\",\"region\":\"\\u9577\\u91ce\\u767a\",\"pageviews_y\":1},{\"title\":\"\\u9577\\u91ce\\u767a \\u30cd\\u30d1\\u30fc\\u30eb\\u65c5\\u884c \\u30cd\\u30d1\\u30fc\\u30eb\\u30c4\\u30a2\\u30fc\\uff5c\\u6d77\\u5916\\u65c5\\u884c \\u6d77\\u5916\\u30c4\\u30a2\\u30fc\\uff5c\\u962a\\u6025\\u4ea4\\u901a\\u793e\",\"pageviews_x\":1,\"pagePath\":\"\\/nepal\\/\",\"region\":\"\\u9577\\u91ce\\u767a\",\"pageviews_y\":1},{\"title\":\"\\u9577\\u91ce\\u767a \\u30e8\\u30fc\\u30ed\\u30c3\\u30d1\\u65c5\\u884c \\u30e8\\u30fc\\u30ed\\u30c3\\u30d1\\u30c4\\u30a2\\u30fc\\uff5c\\u6d77\\u5916\\u65c5\\u884c \\u6d77\\u5916\\u30c4\\u30a2\\u30fc\\uff5c\\u962a\\u6025\\u4ea4\\u901a\\u793e\",\"pageviews_x\":2,\"pagePath\":\"\\/europe\\/\",\"region\":\"\\u9577\\u91ce\\u767a\",\"pageviews_y\":2},{\"title\":\"\\u9577\\u91ce\\u767a \\u30c9\\u30a4\\u30c4\\u65c5\\u884c \\u30c9\\u30a4\\u30c4\\u30c4\\u30a2\\u30fc\\uff5c\\u6d77\\u5916\\u65c5\\u884c \\u6d77\\u5916\\u30c4\\u30a2\\u30fc\\uff5c\\u962a\\u6025\\u4ea4\\u901a\\u793e\",\"pageviews_x\":5,\"pagePath\":\"\\/germany\\/\",\"region\":\"\\u9577\\u91ce\\u767a\",\"pageviews_y\":5},{\"title\":\"\\u9577\\u91ce\\u767a \\u30ce\\u30a4\\u30b7\\u30e5\\u30d0\\u30f3\\u30b7\\u30e5\\u30bf\\u30a4\\u30f3\\u57ce\\u65c5\\u884c \\u30ce\\u30a4\\u30b7\\u30e5\\u30d0\\u30f3\\u30b7\\u30e5\\u30bf\\u30a4\\u30f3\\u57ce\\u30c4\\u30a2\\u30fc\\uff5c\\u6d77\\u5916\\u65c5\\u884c \\u6d77\\u5916\\u30c4\\u30a2\\u30fc\\uff5c\\u962a\\u6025\\u4ea4\\u901a\\u793e\",\"pageviews_x\":2,\"pagePath\":\"\\/germany\\/neuschwanstein\\/\",\"region\":\"\\u9577\\u91ce\\u767a\",\"pageviews_y\":2},{\"title\":\"\\u9577\\u91ce\\u767a \\u30b9\\u30da\\u30a4\\u30f3\\u65c5\\u884c \\u30b9\\u30da\\u30a4\\u30f3\\u30c4\\u30a2\\u30fc\\uff5c\\u6d77\\u5916\\u65c5\\u884c \\u6d77\\u5916\\u30c4\\u30a2\\u30fc\\uff5c\\u962a\\u6025\\u4ea4\\u901a\\u793e\",\"pageviews_x\":1,\"pagePath\":\"\\/spain\\/\",\"region\":\"\\u9577\\u91ce\\u767a\",\"pageviews_y\":1},{\"title\":\"\\u9577\\u91ce\\u767a \\u30dd\\u30eb\\u30c8\\u30ac\\u30eb\\u65c5\\u884c \\u30dd\\u30eb\\u30c8\\u30ac\\u30eb\\u30c4\\u30a2\\u30fc\\uff5c\\u6d77\\u5916\\u65c5\\u884c \\u6d77\\u5916\\u30c4\\u30a2\\u30fc\\uff5c\\u962a\\u6025\\u4ea4\\u901a\\u793e\",\"pageviews_x\":3,\"pagePath\":\"\\/portugal\\/\",\"region\":\"\\u9577\\u91ce\\u767a\",\"pageviews_y\":3},{\"title\":\"\\u9577\\u91ce\\u767a \\u30d0\\u30eb\\u30c8\\u4e09\\u56fd\\u65c5\\u884c \\u30d0\\u30eb\\u30c8\\u4e09\\u56fd\\u30c4\\u30a2\\u30fc\\uff5c\\u6d77\\u5916\\u65c5\\u884c \\u6d77\\u5916\\u30c4\\u30a2\\u30fc\\uff5c\\u962a\\u6025\\u4ea4\\u901a\\u793e\",\"pageviews_x\":2,\"pagePath\":\"\\/baltic\\/\",\"region\":\"\\u9577\\u91ce\\u767a\",\"pageviews_y\":2},{\"title\":\"\\u9577\\u91ce\\u767a \\u30e2\\u30ed\\u30c3\\u30b3\\u65c5\\u884c \\u30e2\\u30ed\\u30c3\\u30b3\\u30c4\\u30a2\\u30fc\\uff5c\\u6d77\\u5916\\u65c5\\u884c \\u6d77\\u5916\\u30c4\\u30a2\\u30fc\\uff5c\\u962a\\u6025\\u4ea4\\u901a\\u793e\",\"pageviews_x\":1,\"pagePath\":\"\\/morocco\\/\",\"region\":\"\\u9577\\u91ce\\u767a\",\"pageviews_y\":1},{\"title\":\"\\u9577\\u91ce\\u767a \\u30c8\\u30eb\\u30b3\\u65c5\\u884c \\u30c8\\u30eb\\u30b3\\u30c4\\u30a2\\u30fc\\uff5c\\u6d77\\u5916\\u65c5\\u884c \\u6d77\\u5916\\u30c4\\u30a2\\u30fc\\uff5c\\u962a\\u6025\\u4ea4\\u901a\\u793e\",\"pageviews_x\":1,\"pagePath\":\"\\/turkey\\/\",\"region\":\"\\u9577\\u91ce\\u767a\",\"pageviews_y\":1},{\"title\":\"\\u9577\\u91ce\\u767a \\u30e9\\u30b9\\u30d9\\u30ac\\u30b9\\u65c5\\u884c \\u30e9\\u30b9\\u30d9\\u30ac\\u30b9\\u30c4\\u30a2\\u30fc\\uff5c\\u6d77\\u5916\\u65c5\\u884c \\u6d77\\u5916\\u30c4\\u30a2\\u30fc\\uff5c\\u962a\\u6025\\u4ea4\\u901a\\u793e\",\"pageviews_x\":1,\"pagePath\":\"\\/america\\/lasvegas\\/\",\"region\":\"\\u9577\\u91ce\\u767a\",\"pageviews_y\":1},{\"title\":\"\\u9577\\u91ce\\u767a \\u30ab\\u30ca\\u30c0\\u65c5\\u884c \\u30ab\\u30ca\\u30c0\\u30c4\\u30a2\\u30fc\\uff5c\\u6d77\\u5916\\u65c5\\u884c \\u6d77\\u5916\\u30c4\\u30a2\\u30fc\\uff5c\\u962a\\u6025\\u4ea4\\u901a\\u793e\",\"pageviews_x\":2,\"pagePath\":\"\\/canada\\/\",\"region\":\"\\u9577\\u91ce\\u767a\",\"pageviews_y\":2},{\"title\":\"\\u9577\\u91ce\\u767a \\u30da\\u30eb\\u30fc\\u65c5\\u884c \\u30da\\u30eb\\u30fc\\u30c4\\u30a2\\u30fc\\uff5c\\u6d77\\u5916\\u65c5\\u884c \\u6d77\\u5916\\u30c4\\u30a2\\u30fc\\uff5c\\u962a\\u6025\\u4ea4\\u901a\\u793e\",\"pageviews_x\":1,\"pagePath\":\"\\/peru\\/\",\"region\":\"\\u9577\\u91ce\\u767a\",\"pageviews_y\":1},{\"title\":\"\\u9577\\u91ce\\u767a \\u30aa\\u30fc\\u30b9\\u30c8\\u30e9\\u30ea\\u30a2\\u65c5\\u884c \\u30aa\\u30fc\\u30b9\\u30c8\\u30e9\\u30ea\\u30a2\\u30c4\\u30a2\\u30fc\\uff5c\\u6d77\\u5916\\u65c5\\u884c \\u6d77\\u5916\\u30c4\\u30a2\\u30fc\\uff5c\\u962a\\u6025\\u4ea4\\u901a\\u793e\",\"pageviews_x\":2,\"pagePath\":\"\\/australia\\/\",\"region\":\"\\u9577\\u91ce\\u767a\",\"pageviews_y\":2},{\"title\":\"\\u9577\\u91ce\\u767a \\u30cf\\u30ef\\u30a4\\u65c5\\u884c \\u30cf\\u30ef\\u30a4\\u30c4\\u30a2\\u30fc\\uff5c\\u6d77\\u5916\\u65c5\\u884c \\u6d77\\u5916\\u30c4\\u30a2\\u30fc\\uff5c\\u962a\\u6025\\u4ea4\\u901a\\u793e\",\"pageviews_x\":3,\"pagePath\":\"\\/hawaii\\/\",\"region\":\"\\u9577\\u91ce\\u767a\",\"pageviews_y\":3},{\"title\":\"\\u9577\\u91ce\\u767a \\u30de\\u30a6\\u30a4\\u5cf6\\u65c5\\u884c \\u30de\\u30a6\\u30a4\\u5cf6\\u30c4\\u30a2\\u30fc\\uff5c\\u6d77\\u5916\\u65c5\\u884c \\u6d77\\u5916\\u30c4\\u30a2\\u30fc\\uff5c\\u962a\\u6025\\u4ea4\\u901a\\u793e\",\"pageviews_x\":1,\"pagePath\":\"\\/hawaii\\/maui\\/\",\"region\":\"\\u9577\\u91ce\\u767a\",\"pageviews_y\":1},{\"title\":\"\\u9577\\u91ce\\u767a \\u30b0\\u30a2\\u30e0\\u65c5\\u884c \\u30b0\\u30a2\\u30e0\\u30c4\\u30a2\\u30fc\\uff5c\\u6d77\\u5916\\u65c5\\u884c \\u6d77\\u5916\\u30c4\\u30a2\\u30fc\\uff5c\\u962a\\u6025\\u4ea4\\u901a\\u793e\",\"pageviews_x\":1,\"pagePath\":\"\\/guam\\/\",\"region\":\"\\u9577\\u91ce\\u767a\",\"pageviews_y\":1}]" , "[{\"title\":\"\\u9577\\u91ce\\u767a \\u30c1\\u30d9\\u30c3\\u30c8\\u65c5\\u884c \\u30c1\\u30d9\\u30c3\\u30c8\\u30c4\\u30a2\\u30fc\\uff5c\\u6d77\\u5916\\u65c5\\u884c \\u6d77\\u5916\\u30c4\\u30a2\\u30fc\\uff5c\\u962a\\u6025\\u4ea4\\u901a\\u793e\",\"pageviews_x\":1,\"pagePath\":\"\\/china\\/tibet\\/\",\"region\":\"\\u9577\\u91ce\\u767a\",\"pageviews_y\":1},{\"title\":\"\\u9577\\u91ce\\u767a \\u97d3\\u56fd\\u65c5\\u884c \\u97d3\\u56fd\\u30c4\\u30a2\\u30fc\\uff5c\\u6d77\\u5916\\u65c5\\u884c \\u6d77\\u5916\\u30c4\\u30a2\\u30fc\\uff5c\\u962a\\u6025\\u4ea4\\u901a\\u793e\",\"pageviews_x\":2,\"pagePath\":\"\\/korea\\/\",\"region\":\"\\u9577\\u91ce\\u767a\",\"pageviews_y\":3},{\"title\":\"\\u9577\\u91ce\\u767a \\u30bd\\u30a6\\u30eb\\u65c5\\u884c \\u30bd\\u30a6\\u30eb\\u30c4\\u30a2\\u30fc\\uff5c\\u6d77\\u5916\\u65c5\\u884c \\u6d77\\u5916\\u30c4\\u30a2\\u30fc\\uff5c\\u962a\\u6025\\u4ea4\\u901a\\u793e\",\"pageviews_x\":1,\"pagePath\":\"\\/korea\\/seoul\\/\",\"region\":\"\\u9577\\u91ce\\u767a\",\"pageviews_y\":2},{\"title\":\"\\u9577\\u91ce\\u767a \\u6e08\\u5dde\\u5cf6\\u65c5\\u884c \\u6e08\\u5dde\\u5cf6\\u30c4\\u30a2\\u30fc\\uff5c\\u6d77\\u5916\\u65c5\\u884c \\u6d77\\u5916\\u30c4\\u30a2\\u30fc\\uff5c\\u962a\\u6025\\u4ea4\\u901a\\u793e\",\"pageviews_x\":1,\"pagePath\":\"\\/korea\\/jeju\\/\",\"region\":\"\\u9577\\u91ce\\u767a\",\"pageviews_y\":1},{\"title\":\"\\u9577\\u91ce\\u767a \\u53f0\\u6e7e\\u65c5\\u884c \\u53f0\\u6e7e\\u30c4\\u30a2\\u30fc\\uff5c\\u6d77\\u5916\\u65c5\\u884c \\u6d77\\u5916\\u30c4\\u30a2\\u30fc\\uff5c\\u962a\\u6025\\u4ea4\\u901a\\u793e\",\"pageviews_x\":5,\"pagePath\":\"\\/taiwan\\/\",\"region\":\"\\u9577\\u91ce\\u767a\",\"pageviews_y\":9},{\"title\":\"\\u9577\\u91ce\\u767a \\u53f0\\u5317\\u65c5\\u884c \\u53f0\\u5317\\u30c4\\u30a2\\u30fc\\uff5c\\u6d77\\u5916\\u65c5\\u884c \\u6d77\\u5916\\u30c4\\u30a2\\u30fc\\uff5c\\u962a\\u6025\\u4ea4\\u901a\\u793e\",\"pageviews_x\":3,\"pagePath\":\"\\/taiwan\\/taipei\\/\",\"region\":\"\\u9577\\u91ce\\u767a\",\"pageviews_y\":3},{\"title\":\"\\u9577\\u91ce\\u767a \\u30bf\\u30a4\\u65c5\\u884c \\u30bf\\u30a4\\u30c4\\u30a2\\u30fc\\uff5c\\u6d77\\u5916\\u65c5\\u884c \\u6d77\\u5916\\u30c4\\u30a2\\u30fc\\uff5c\\u962a\\u6025\\u4ea4\\u901a\\u793e\",\"pageviews_x\":2,\"pagePath\":\"\\/thailand\\/\",\"region\":\"\\u9577\\u91ce\\u767a\",\"pageviews_y\":2},{\"title\":\"\\u9577\\u91ce\\u767a \\u30b7\\u30f3\\u30ac\\u30dd\\u30fc\\u30eb\\u65c5\\u884c \\u30b7\\u30f3\\u30ac\\u30dd\\u30fc\\u30eb\\u30c4\\u30a2\\u30fc\\uff5c\\u6d77\\u5916\\u65c5\\u884c \\u6d77\\u5916\\u30c4\\u30a2\\u30fc\\uff5c\\u962a\\u6025\\u4ea4\\u901a\\u793e\",\"pageviews_x\":1,\"pagePath\":\"\\/singapore\\/\",\"region\":\"\\u9577\\u91ce\\u767a\",\"pageviews_y\":2},{\"title\":\"\\u9577\\u91ce\\u767a \\u30de\\u30ec\\u30fc\\u30b7\\u30a2\\u65c5\\u884c \\u30de\\u30ec\\u30fc\\u30b7\\u30a2\\u30c4\\u30a2\\u30fc\\uff5c\\u6d77\\u5916\\u65c5\\u884c \\u6d77\\u5916\\u30c4\\u30a2\\u30fc\\uff5c\\u962a\\u6025\\u4ea4\\u901a\\u793e\",\"pageviews_x\":1,\"pagePath\":\"\\/malaysia\\/\",\"region\":\"\\u9577\\u91ce\\u767a\",\"pageviews_y\":1},{\"title\":\"\\u9577\\u91ce\\u767a \\u30d9\\u30c8\\u30ca\\u30e0\\u65c5\\u884c \\u30d9\\u30c8\\u30ca\\u30e0\\u30c4\\u30a2\\u30fc\\uff5c\\u6d77\\u5916\\u65c5\\u884c \\u6d77\\u5916\\u30c4\\u30a2\\u30fc\\uff5c\\u962a\\u6025\\u4ea4\\u901a\\u793e\",\"pageviews_x\":1,\"pagePath\":\"\\/vietnam\\/\",\"region\":\"\\u9577\\u91ce\\u767a\",\"pageviews_y\":1},{\"title\":\"\\u9577\\u91ce\\u767a \\u30cd\\u30d1\\u30fc\\u30eb\\u65c5\\u884c \\u30cd\\u30d1\\u30fc\\u30eb\\u30c4\\u30a2\\u30fc\\uff5c\\u6d77\\u5916\\u65c5\\u884c \\u6d77\\u5916\\u30c4\\u30a2\\u30fc\\uff5c\\u962a\\u6025\\u4ea4\\u901a\\u793e\",\"pageviews_x\":1,\"pagePath\":\"\\/nepal\\/\",\"region\":\"\\u9577\\u91ce\\u767a\",\"pageviews_y\":1},{\"title\":\"\\u9577\\u91ce\\u767a \\u30e8\\u30fc\\u30ed\\u30c3\\u30d1\\u65c5\\u884c \\u30e8\\u30fc\\u30ed\\u30c3\\u30d1\\u30c4\\u30a2\\u30fc\\uff5c\\u6d77\\u5916\\u65c5\\u884c \\u6d77\\u5916\\u30c4\\u30a2\\u30fc\\uff5c\\u962a\\u6025\\u4ea4\\u901a\\u793e\",\"pageviews_x\":2,\"pagePath\":\"\\/europe\\/\",\"region\":\"\\u9577\\u91ce\\u767a\",\"pageviews_y\":2},{\"title\":\"\\u9577\\u91ce\\u767a \\u30c9\\u30a4\\u30c4\\u65c5\\u884c \\u30c9\\u30a4\\u30c4\\u30c4\\u30a2\\u30fc\\uff5c\\u6d77\\u5916\\u65c5\\u884c \\u6d77\\u5916\\u30c4\\u30a2\\u30fc\\uff5c\\u962a\\u6025\\u4ea4\\u901a\\u793e\",\"pageviews_x\":5,\"pagePath\":\"\\/germany\\/\",\"region\":\"\\u9577\\u91ce\\u767a\",\"pageviews_y\":5},{\"title\":\"\\u9577\\u91ce\\u767a \\u30ce\\u30a4\\u30b7\\u30e5\\u30d0\\u30f3\\u30b7\\u30e5\\u30bf\\u30a4\\u30f3\\u57ce\\u65c5\\u884c \\u30ce\\u30a4\\u30b7\\u30e5\\u30d0\\u30f3\\u30b7\\u30e5\\u30bf\\u30a4\\u30f3\\u57ce\\u30c4\\u30a2\\u30fc\\uff5c\\u6d77\\u5916\\u65c5\\u884c \\u6d77\\u5916\\u30c4\\u30a2\\u30fc\\uff5c\\u962a\\u6025\\u4ea4\\u901a\\u793e\",\"pageviews_x\":2,\"pagePath\":\"\\/germany\\/neuschwanstein\\/\",\"region\":\"\\u9577\\u91ce\\u767a\",\"pageviews_y\":2},{\"title\":\"\\u9577\\u91ce\\u767a \\u30b9\\u30da\\u30a4\\u30f3\\u65c5\\u884c \\u30b9\\u30da\\u30a4\\u30f3\\u30c4\\u30a2\\u30fc\\uff5c\\u6d77\\u5916\\u65c5\\u884c \\u6d77\\u5916\\u30c4\\u30a2\\u30fc\\uff5c\\u962a\\u6025\\u4ea4\\u901a\\u793e\",\"pageviews_x\":1,\"pagePath\":\"\\/spain\\/\",\"region\":\"\\u9577\\u91ce\\u767a\",\"pageviews_y\":1},{\"title\":\"\\u9577\\u91ce\\u767a \\u30dd\\u30eb\\u30c8\\u30ac\\u30eb\\u65c5\\u884c \\u30dd\\u30eb\\u30c8\\u30ac\\u30eb\\u30c4\\u30a2\\u30fc\\uff5c\\u6d77\\u5916\\u65c5\\u884c \\u6d77\\u5916\\u30c4\\u30a2\\u30fc\\uff5c\\u962a\\u6025\\u4ea4\\u901a\\u793e\",\"pageviews_x\":3,\"pagePath\":\"\\/portugal\\/\",\"region\":\"\\u9577\\u91ce\\u767a\",\"pageviews_y\":3},{\"title\":\"\\u9577\\u91ce\\u767a \\u30d0\\u30eb\\u30c8\\u4e09\\u56fd\\u65c5\\u884c \\u30d0\\u30eb\\u30c8\\u4e09\\u56fd\\u30c4\\u30a2\\u30fc\\uff5c\\u6d77\\u5916\\u65c5\\u884c \\u6d77\\u5916\\u30c4\\u30a2\\u30fc\\uff5c\\u962a\\u6025\\u4ea4\\u901a\\u793e\",\"pageviews_x\":2,\"pagePath\":\"\\/baltic\\/\",\"region\":\"\\u9577\\u91ce\\u767a\",\"pageviews_y\":2},{\"title\":\"\\u9577\\u91ce\\u767a \\u30e2\\u30ed\\u30c3\\u30b3\\u65c5\\u884c \\u30e2\\u30ed\\u30c3\\u30b3\\u30c4\\u30a2\\u30fc\\uff5c\\u6d77\\u5916\\u65c5\\u884c \\u6d77\\u5916\\u30c4\\u30a2\\u30fc\\uff5c\\u962a\\u6025\\u4ea4\\u901a\\u793e\",\"pageviews_x\":1,\"pagePath\":\"\\/morocco\\/\",\"region\":\"\\u9577\\u91ce\\u767a\",\"pageviews_y\":1},{\"title\":\"\\u9577\\u91ce\\u767a \\u30c8\\u30eb\\u30b3\\u65c5\\u884c \\u30c8\\u30eb\\u30b3\\u30c4\\u30a2\\u30fc\\uff5c\\u6d77\\u5916\\u65c5\\u884c \\u6d77\\u5916\\u30c4\\u30a2\\u30fc\\uff5c\\u962a\\u6025\\u4ea4\\u901a\\u793e\",\"pageviews_x\":1,\"pagePath\":\"\\/turkey\\/\",\"region\":\"\\u9577\\u91ce\\u767a\",\"pageviews_y\":1},{\"title\":\"\\u9577\\u91ce\\u767a \\u30e9\\u30b9\\u30d9\\u30ac\\u30b9\\u65c5\\u884c \\u30e9\\u30b9\\u30d9\\u30ac\\u30b9\\u30c4\\u30a2\\u30fc\\uff5c\\u6d77\\u5916\\u65c5\\u884c \\u6d77\\u5916\\u30c4\\u30a2\\u30fc\\uff5c\\u962a\\u6025\\u4ea4\\u901a\\u793e\",\"pageviews_x\":1,\"pagePath\":\"\\/america\\/lasvegas\\/\",\"region\":\"\\u9577\\u91ce\\u767a\",\"pageviews_y\":1},{\"title\":\"\\u9577\\u91ce\\u767a \\u30ab\\u30ca\\u30c0\\u65c5\\u884c \\u30ab\\u30ca\\u30c0\\u30c4\\u30a2\\u30fc\\uff5c\\u6d77\\u5916\\u65c5\\u884c \\u6d77\\u5916\\u30c4\\u30a2\\u30fc\\uff5c\\u962a\\u6025\\u4ea4\\u901a\\u793e\",\"pageviews_x\":2,\"pagePath\":\"\\/canada\\/\",\"region\":\"\\u9577\\u91ce\\u767a\",\"pageviews_y\":2},{\"title\":\"\\u9577\\u91ce\\u767a \\u30da\\u30eb\\u30fc\\u65c5\\u884c \\u30da\\u30eb\\u30fc\\u30c4\\u30a2\\u30fc\\uff5c\\u6d77\\u5916\\u65c5\\u884c \\u6d77\\u5916\\u30c4\\u30a2\\u30fc\\uff5c\\u962a\\u6025\\u4ea4\\u901a\\u793e\",\"pageviews_x\":1,\"pagePath\":\"\\/peru\\/\",\"region\":\"\\u9577\\u91ce\\u767a\",\"pageviews_y\":1},{\"title\":\"\\u9577\\u91ce\\u767a \\u30aa\\u30fc\\u30b9\\u30c8\\u30e9\\u30ea\\u30a2\\u65c5\\u884c \\u30aa\\u30fc\\u30b9\\u30c8\\u30e9\\u30ea\\u30a2\\u30c4\\u30a2\\u30fc\\uff5c\\u6d77\\u5916\\u65c5\\u884c \\u6d77\\u5916\\u30c4\\u30a2\\u30fc\\uff5c\\u962a\\u6025\\u4ea4\\u901a\\u793e\",\"pageviews_x\":2,\"pagePath\":\"\\/australia\\/\",\"region\":\"\\u9577\\u91ce\\u767a\",\"pageviews_y\":2},{\"title\":\"\\u9577\\u91ce\\u767a \\u30cf\\u30ef\\u30a4\\u65c5\\u884c \\u30cf\\u30ef\\u30a4\\u30c4\\u30a2\\u30fc\\uff5c\\u6d77\\u5916\\u65c5\\u884c \\u6d77\\u5916\\u30c4\\u30a2\\u30fc\\uff5c\\u962a\\u6025\\u4ea4\\u901a\\u793e\",\"pageviews_x\":3,\"pagePath\":\"\\/hawaii\\/\",\"region\":\"\\u9577\\u91ce\\u767a\",\"pageviews_y\":3},{\"title\":\"\\u9577\\u91ce\\u767a \\u30de\\u30a6\\u30a4\\u5cf6\\u65c5\\u884c \\u30de\\u30a6\\u30a4\\u5cf6\\u30c4\\u30a2\\u30fc\\uff5c\\u6d77\\u5916\\u65c5\\u884c \\u6d77\\u5916\\u30c4\\u30a2\\u30fc\\uff5c\\u962a\\u6025\\u4ea4\\u901a\\u793e\",\"pageviews_x\":1,\"pagePath\":\"\\/hawaii\\/maui\\/\",\"region\":\"\\u9577\\u91ce\\u767a\",\"pageviews_y\":1},{\"title\":\"\\u9577\\u91ce\\u767a \\u30b0\\u30a2\\u30e0\\u65c5\\u884c \\u30b0\\u30a2\\u30e0\\u30c4\\u30a2\\u30fc\\uff5c\\u6d77\\u5916\\u65c5\\u884c \\u6d77\\u5916\\u30c4\\u30a2\\u30fc\\uff5c\\u962a\\u6025\\u4ea4\\u901a\\u793e\",\"pageviews_x\":1,\"pagePath\":\"\\/guam\\/\",\"region\":\"\\u9577\\u91ce\\u767a\",\"pageviews_y\":1}]"]