{
"inter":[
{"name":"アジア","path":"/asia/"},
{"name":"中国","path":"/china/"},
{"name":"北京","path":"/china/beijing/"},
{"name":"上海","path":"/china/shanghai/"},
{"name":"大連","path":"/china/dalian/"},
{"name":"杭州","path":"/china/hangzhou/"},
{"name":"成都","path":"/china/chengdu/"},
{"name":"西安","path":"/china/xian/"},
{"name":"九寨溝・黄龍","path":"/china/jiuzhaigou/"},
{"name":"チベット","path":"/china/tibet/"},
{"name":"韓国","path":"/korea/"},
{"name":"ソウル","path":"/korea/seoul/"},
{"name":"釜山","path":"/korea/busan/"},
{"name":"済州島","path":"/korea/jeju/"},
{"name":"台湾","path":"/taiwan/"},
{"name":"太魯閣","path":"/taiwan/taroko/"},
{"name":"日月潭","path":"/taiwan/sunmoonlake/"},
{"name":"台北","path":"/taiwan/taipei/"},
{"name":"台中","path":"/taiwan/taichung/"},
{"name":"台南","path":"/taiwan/tainan/"},
{"name":"高雄","path":"/taiwan/kaohsiung/"},
{"name":"香港","path":"/hongkong/"},
{"name":"マカオ","path":"/macau/"},
{"name":"タイ","path":"/thailand/"},
{"name":"チェンマイ","path":"/thailand/chiangmai/"},
{"name":"バンコク","path":"/thailand/bangkok/"},
{"name":"プーケット","path":"/thailand/phuket/"},
{"name":"シンガポール","path":"/singapore/"},
{"name":"マレーシア","path":"/malaysia/"},
{"name":"フィリピン","path":"/philippines/"},
{"name":"インドネシア","path":"/asian-beach/"},
{"name":"ベトナム","path":"/vietnam/"},
{"name":"ハノイ","path":"/vietnam/hanoi/"},
{"name":"ハロン湾","path":"/vietnam/halon/"},
{"name":"ホイアン","path":"/vietnam/hoian/"},
{"name":"ホーチミン","path":"/vietnam/hochiminh/"},
{"name":"カンボジア","path":"/cambodia/"},
{"name":"ラオス","path":"/laos/"},
{"name":"インド","path":"/india/"},
{"name":"ネパール","path":"/nepal/"},
{"name":"ミャンマー","path":"/myanmar/"},
{"name":"スリランカ","path":"/srilanka/"},
{"name":"モルディブ","path":"/maldives/"},
{"name":"ヨーロッパ","path":"/europe/"},
{"name":"フランス","path":"/france/"},
{"name":"アルル","path":"/france/arles/"},
{"name":"パリ","path":"/france/paris/"},
{"name":"モンサンミッシェル","path":"/france/montstmichel/"},
{"name":"ロワール","path":"/france/loire/"},
{"name":"ニース","path":"/france/nice/"},
{"name":"プロヴァンス","path":"/france/provence/"},
{"name":"ボルドー","path":"/france/bordeaux/"},
{"name":"リヨン","path":"/france/lyon/"},
{"name":"イギリス","path":"/uk/"},
{"name":"ロンドン","path":"/uk/london/"},
{"name":"湖水地方","path":"/uk/lakedistrict/"},
{"name":"コッツウォルズ","path":"/uk/cotswolds/"},
{"name":"エジンバラ","path":"/uk/edinburgh/"},
{"name":"ストラトフォード アポン エイボン","path":"/uk/stratford-upon-avon/"},
{"name":"アイルランド","path":"/ireland/"},
{"name":"イタリア","path":"/italy/"},
{"name":"ローマ","path":"/italy/roma/"},
{"name":"ベネチア","path":"/italy/venezia/"},
{"name":"ミラノ","path":"/italy/milano/"},
{"name":"フィレンツェ","path":"/italy/firenze/"},
{"name":"ナポリ","path":"/italy/napoli/"},
{"name":"カプリ島","path":"/italy/capri/"},
{"name":"アルベロベッロ","path":"/italy/alberobello/"},
{"name":"アマルフィ","path":"/italy/amalfi/"},
{"name":"ピサ","path":"/italy/pisa/"},
{"name":"シチリア島","path":"/italy/sicilia/"},
{"name":"マテーラ","path":"/italy/matera/"},
{"name":"マルタ","path":"/malta/"},
{"name":"ギリシャ","path":"/greece/"},
{"name":"スイス","path":"/swiss/"},
{"name":"インターラーケン","path":"/swiss/interlaken/"},
{"name":"グリンデルワルド","path":"/swiss/grindelwald/"},
{"name":"サンモリッツ","path":"/swiss/stmoritz/"},
{"name":"ジュネーブ","path":"/swiss/geneve/"},
{"name":"チューリッヒ","path":"/swiss/zurich/"},
{"name":"バーゼル","path":"/swiss/basel/"},
{"name":"ユングフラウ","path":"/swiss/jungfrau/"},
{"name":"クライネシャイデック","path":"/swiss/kleine-scheidegg/"},
{"name":"モンブラン","path":"/swiss/montblanc/"},
{"name":"ドイツ","path":"/germany/"},
{"name":"ローテンブルク","path":"/germany/rothenburg/"},
{"name":"フランクフルト","path":"/germany/frankfurt/"},
{"name":"ノイシュバンシュタイン城","path":"/germany/neuschwanstein/"},
{"name":"ハイデルベルク","path":"/germany/heidelberg/"},
{"name":"ベルリン","path":"/germany/berlin/"},
{"name":"ミュンヘン","path":"/germany/munchen/"},
{"name":"オランダ","path":"/holland/"},
{"name":"アムステルダム","path":"/holland/amsterdam/"},
{"name":"キューケンホフ","path":"/holland/keukenhof/"},
{"name":"キンデルダイク","path":"/holland/kinderdijk/"},
{"name":"ハーグ","path":"/holland/haag/"},
{"name":"ベルギー","path":"/belgium/"},
{"name":"アントワープ","path":"/belgium/antwerp/"},
{"name":"ゲント","path":"/belgium/gent/"},
{"name":"ブリュッセル","path":"/belgium/bruxelles/"},
{"name":"ブルージュ","path":"/belgium/bruges/"},
{"name":"スペイン","path":"/spain/"},
{"name":"バルセロナ","path":"/spain/barcelona/"},
{"name":"マドリッド","path":"/spain/madrid/"},
{"name":"トレド","path":"/spain/toledo/"},
{"name":"ミハス","path":"/spain/mijas/"},
{"name":"ラ・マンチャ","path":"/spain/la-mancha/"},
{"name":"セゴビア","path":"/spain/segovia/"},
{"name":"セビリア","path":"/spain/sevilla/"},
{"name":"グラナダ","path":"/spain/granada/"},
{"name":"サンティアゴ・デ・コンポステーラ","path":"/spain/santiago/"},
{"name":"ポルトガル","path":"/portugal/"},
{"name":"リスボン","path":"/portugal/lisbon/"},
{"name":"ポルト","path":"/portugal/porto/"},
{"name":"北欧","path":"/northern-eur/"},
{"name":"デンマーク","path":"/denmark/"},
{"name":"ノルウェー","path":"/norway/"},
{"name":"スウェーデン","path":"/sweden/"},
{"name":"フィンランド","path":"/finland/"},
{"name":"アイスランド","path":"/iceland/"},
{"name":"ロシア","path":"/russia/"},
{"name":"東欧・中欧","path":"/east-eur/"},
{"name":"オーストリア","path":"/austria/"},
{"name":"チェコ","path":"/czech/"},
{"name":"スロバキア","path":"/slovakia/"},
{"name":"ハンガリー","path":"/hungary/"},
{"name":"ポーランド","path":"/poland/"},
{"name":"ルーマニア","path":"/rumania/"},
{"name":"ブルガリア","path":"/bulgaria/"},
{"name":"クロアチア・スロベニア","path":"/croatia-slovenia/"},
{"name":"ウィーン","path":"/austria/wien/"},
{"name":"ザルツブルク","path":"/austria/salzburg/"},
{"name":"ザルツカンマーグート","path":"/austria/salzkammergut/"},
{"name":"グラーツ","path":"/austria/graz/"},
{"name":"インスブルック","path":"/austria/innsbruck/"},
{"name":"ハルシュタット","path":"/austria/hallstatt/"},
{"name":"バルト三国","path":"/baltic/"},
{"name":"アフリカ","path":"/africa/"},
{"name":"エジプト","path":"/egypt/"},
{"name":"アブ シンベル","path":"/egypt/abusimbel/"},
{"name":"アレキサンドリア","path":"/egypt/alexandria/"},
{"name":"カイロ","path":"/egypt/cairo/"},
{"name":"ギザ","path":"/egypt/giza/"},
{"name":"シナイ半島","path":"/egypt/sinai/"},
{"name":"ルクソール","path":"/egypt/luxor/"},
{"name":"チュニジア","path":"/tunisia/"},
{"name":"モロッコ","path":"/morocco/"},
{"name":"南アフリカ","path":"/south-africa/"},
{"name":"ケニア","path":"/kenya/"},
{"name":"ボツワナ","path":"/botswana/"},
{"name":"ジンバブエ・ザンビア","path":"/jinbabue-zanvia/"},
{"name":"タンザニア","path":"/tanzania/"},
{"name":"中近東","path":"/middle-east/"},
{"name":"トルコ","path":"/turkey/"},
{"name":"イスタンブール","path":"/turkey/istanbul/"},
{"name":"カッパドキア","path":"/turkey/cappadocia/"},
{"name":"トロイ","path":"/turkey/troy/"},
{"name":"パムッカレ","path":"/turkey/pamukkale/"},
{"name":"ヨルダン","path":"/jordan/"},
{"name":"イスラエル","path":"/israel/"},
{"name":"アラブ首長国連邦","path":"/uae/"},
{"name":"イラン","path":"/iran/"},
{"name":"ウズベキスタン","path":"/uzbekistan/"},
{"name":"北米","path":"/north-america/"},
{"name":"アメリカ","path":"/america/"},
{"name":"ロサンゼルス","path":"/america/la/"},
{"name":"ラスベガス","path":"/america/lasvegas/"},
{"name":"グランドキャニオン","path":"/america/grandcanyon/"},
{"name":"サンフランシスコ","path":"/america/sanfrancisco/"},
{"name":"ヨセミテ","path":"/america/yosemite/"},
{"name":"シアトル","path":"/america/seattle/"},
{"name":"ニューヨーク","path":"/america/ny/"},
{"name":"ボストン","path":"/america/boston/"},
{"name":"オーランド","path":"/america/orlando/"},
{"name":"アラスカ","path":"/america/alaska/"},
{"name":"イエローストーン国立公園","path":"/america/yellowstone/"},
{"name":"ワシントンB.C.","path":"/america/washington/"},
{"name":"ヒューストン","path":"/america/houston/"},
{"name":"カナダ","path":"/canada/"},
{"name":"バンクーバー","path":"/canada/vancouver/"},
{"name":"カナディアンロッキー","path":"/canada/rockies/"},
{"name":"ナイアガラ","path":"/canada/niagara/"},
{"name":"トロント","path":"/canada/toronto/"},
{"name":"ケベック","path":"/canada/quebec/"},
{"name":"モントリオール","path":"/canada/montreal/"},
{"name":"プリンスエドワード島","path":"/canada/pei/"},
{"name":"イエローナイフ","path":"/canada/yellowknife/"},
{"name":"ビクトリア","path":"/canada/victoria/"},
{"name":"ローレンシャン高原","path":"/canada/laurentian/"},
{"name":"中南米","path":"/latin-america/"},
{"name":"メキシコ","path":"/mexico/"},
{"name":"ブラジル","path":"/brazil/"},
{"name":"エクアドル","path":"/ecuador/"},
{"name":"ベネズエラ","path":"/venezuela/"},
{"name":"ペルー","path":"/peru/"},
{"name":"マチュピチュ","path":"/peru/machupicchu/"},
{"name":"ナスカ","path":"/peru/nazca/"},
{"name":"クスコ","path":"/peru/cuzco/"},
{"name":"プーノ","path":"/peru/puno/"},
{"name":"リマ","path":"/peru/lima/"},
{"name":"アルゼンチン","path":"/argentina/"},
{"name":"オセアニア","path":"/oceania/"},
{"name":"オーストラリア","path":"/australia/"},
{"name":"シドニー","path":"/australia/sydney/"},
{"name":"ゴールドコースト","path":"/australia/goldcoast/"},
{"name":"ケアンズ","path":"/australia/cairns/"},
{"name":"グレートバリアリーフ","path":"/australia/great-barrier-reef/"},
{"name":"エアーズロック","path":"/australia/uluru/"},
{"name":"メルボルン","path":"/australia/melbourne/"},
{"name":"パース","path":"/australia/perth/"},
{"name":"タスマニア島","path":"/australia/tasmania/"},
{"name":"ニュージーランド","path":"/newzealand/"},
{"name":"オークランド","path":"/newzealand/auckland/"},
{"name":"クイーンズタウン","path":"/newzealand/queenstown/"},
{"name":"クライストチャーチ","path":"/newzealand/christchurch/"},
{"name":"テアナウ","path":"/newzealand/teanau/"},
{"name":"マウントクック","path":"/newzealand/mountcook/"},
{"name":"ミルフォードサウンド","path":"/newzealand/milfordsound/"},
{"name":"南太平洋","path":"/s-pacific/"},
{"name":"タヒチ","path":"/tahiti/"},
{"name":"ニューカレドニア","path":"/newcaledonia/"},
{"name":"フィジー","path":"/fiji/"},
{"name":"ハワイ","path":"/hawaii/"},
{"name":"オアフ島（ホノルル）","path":"/hawaii/oahu/"},
{"name":"ハワイ島","path":"/hawaii/bigisland/"},
{"name":"マウイ島","path":"/hawaii/maui/"},
{"name":"カウアイ島","path":"/hawaii/kauai/"},
{"name":"ミクロネシア","path":"/micronesia/"},
{"name":"グアム","path":"/guam/"},
{"name":"サイパン","path":"/saipan/"}]
}
